LICENSE
MANIFEST.in
README.md
setup.py
django_social_auth_appsfuel/__init__.py
django_social_auth_appsfuel/backend.py
django_social_auth_appsfuel.egg-info/PKG-INFO
django_social_auth_appsfuel.egg-info/SOURCES.txt
django_social_auth_appsfuel.egg-info/dependency_links.txt
django_social_auth_appsfuel.egg-info/requires.txt
django_social_auth_appsfuel.egg-info/top_level.txt