Metadata-Version: 1.0
Name: django-social-auth-appsfuel
Version: 1.0.0
Summary: Appsfuel backend for django-social-auth
Home-page: https://github.com/AppsFuel/django-social-auth-appsfuel
Author: Andrea de Marco
Author-email: andrea.demarco@buogiorno.com
License: BSD
Platform: UNKNOWN
